github_project_manager/__init__.py
github_project_manager/_version.py
github_project_manager/api_client.py
github_project_manager/models.py
github_project_manager/project_manager.py
github_project_manager-0.2.0.dist-info/licenses/LICENSE
github_project_manager-0.2.0.dist-info/METADATA
github_project_manager-0.2.0.dist-info/WHEEL
github_project_manager-0.2.0.dist-info/top_level.txt
github_project_manager-0.2.0.dist-info/RECORD
